[
    {
        "content": [
            {
                "x": 61,
                "y": 82.5
            },
            {
                "x": 342,
                "y": 82.5
            },
            {
                "x": 342,
                "y": 233.5
            },
            {
                "x": 61,
                "y": 233.5
            }
        ],
        "rectMask": {
            "xMin": 61,
            "yMin": 82.5,
            "width": 281,
            "height": 151
        },
        "labels": {
            "labelName": "Crab",
            "labelColor": "#ff0000",
            "labelColorRGB": "255,0,0",
            "visibility": false
        },
        "labelLocation": {
            "x": 201.5,
            "y": 158
        },
        "contentType": "rect"
    }
]